pyf16-0.1.1.dist-info/METADATA
pyf16-0.1.1.dist-info/WHEEL
pyf16-0.1.1.dist-info/licenses/LICENSE
pyf16/_core.pyi
pyf16/__init__.py
pyf16/py.typed
pyf16/_core.abi3.so
pyf16-0.1.1.dist-info/RECORD
