Metadata-Version: 2.4
Name: pyf16
Version: 0.1.1
License-File: LICENSE
Summary: A Python package for F-16 aircraft simulation.
Author: WindLX <windlxt@outlook.com>
Author-email: WindLX <windlxt@outlook.com>
Requires-Python: >=3.10
